{"cameraMode":{"drawMode":0,"name":"Shaded","section":"Shading Mode"},"sceneLighting":true,"audioPlay":false,"sceneViewState":{"m_AlwaysRefresh":false,"showFog":true,"showSkybox":true,"showFlares":true,"showImageEffects":true,"showParticleSystems":true,"showVisualEffectGraphs":true,"m_FxEnabled":true},"in2DMode":false,"pivot":{"x":6.96999979019165,"y":19.67609214782715,"z":-63.23338317871094},"rotation":{"x":0.26700058579444888,"y":0.5539129376411438,"z":-0.19345057010650636,"w":0.7645123600959778},"size":17.15567970275879,"orthographic":false}